{
 "songId": "midnight_avenue",
 "difficulty": "Hard",
 "bpm": 112,
 "offsetMs": 0,
 "notes": [
  {
   "type": "tap",
   "lane": 0,
   "startTimeMs": 4821
  },
  {
   "type": "tap",
   "lane": 2,
   "startTimeMs": 5892
  },
  {
   "type": "tap",
   "lane": 3,
   "startTimeMs": 6964
  },
  {
   "type": "tap",
   "lane": 2,
   "startTimeMs": 8035
  },
  {
   "type": "tap",
   "lane": 2,
   "startTimeMs": 9107
  },
  {
   "type": "tap",
   "lane": 0,
   "startTimeMs": 10178
  },
  {
   "type": "tap",
   "lane": 1,
   "startTimeMs": 11250
  },
  {
   "type": "tap",
   "lane": 0,
   "startTimeMs": 12321
  },
  {
   "type": "tap",
   "lane": 1,
   "startTimeMs": 12857
  },
  {
   "type": "tap",
   "lane": 0,
   "startTimeMs": 13392
  },
  {
   "type": "tap",
   "lane": 2,
   "startTimeMs": 14464
  },
  {
   "type": "tap",
   "lane": 3,
   "startTimeMs": 15535
  },
  {
   "type": "tap",
   "lane": 2,
   "startTimeMs": 16607
  },
  {
   "type": "fever",
   "lane": 3,
   "startTimeMs": 17142
  },
  {
   "type": "tap",
   "lane": 2,
   "startTimeMs": 17678
  },
  {
   "type": "tap",
   "lane": 0,
   "startTimeMs": 18750
  },
  {
   "type": "tap",
   "lane": 1,
   "startTimeMs": 19821
  },
  {
   "type": "tap",
   "lane": 0,
   "startTimeMs": 20892
  },
  {
   "type": "golden",
   "lane": 1,
   "startTimeMs": 21428
  },
  {
   "type": "tap",
   "lane": 3,
   "startTimeMs": 21696
  },
  {
   "type": "tap",
   "lane": 2,
   "startTimeMs": 21964
  },
  {
   "type": "hold",
   "lane": 3,
   "startTimeMs": 22500,
   "endTimeMs": 23035
  },
  {
   "type": "tap",
   "lane": 1,
   "startTimeMs": 23035
  },
  {
   "type": "tap",
   "lane": 0,
   "startTimeMs": 23571
  },
  {
   "type": "tap",
   "lane": 1,
   "startTimeMs": 24107
  },
  {
   "type": "hold",
   "lane": 3,
   "startTimeMs": 24642,
   "endTimeMs": 25177
  },
  {
   "type": "tap",
   "lane": 2,
   "startTimeMs": 25178
  },
  {
   "type": "tap",
   "lane": 3,
   "startTimeMs": 25714
  },
  {
   "type": "tap",
   "lane": 1,
   "startTimeMs": 25982
  },
  {
   "type": "tap",
   "lane": 0,
   "startTimeMs": 26250
  },
  {
   "type": "tap",
   "lane": 3,
   "startTimeMs": 27321
  },
  {
   "type": "tap",
   "lane": 2,
   "startTimeMs": 27857
  },
  {
   "type": "tap",
   "lane": 3,
   "startTimeMs": 28392
  },
  {
   "type": "hold",
   "lane": 1,
   "startTimeMs": 28928,
   "endTimeMs": 29463
  },
  {
   "type": "tap",
   "lane": 0,
   "startTimeMs": 29464
  },
  {
   "type": "golden",
   "lane": 1,
   "startTimeMs": 30000
  },
  {
   "type": "tap",
   "lane": 2,
   "startTimeMs": 30535
  },
  {
   "type": "hold",
   "lane": 3,
   "startTimeMs": 31071,
   "endTimeMs": 31606
  },
  {
   "type": "tap",
   "lane": 1,
   "startTimeMs": 31607
  },
  {
   "type": "tap",
   "lane": 1,
   "startTimeMs": 32678
  },
  {
   "type": "hold",
   "lane": 3,
   "startTimeMs": 33214,
   "endTimeMs": 33749
  },
  {
   "type": "tap",
   "lane": 2,
   "startTimeMs": 33749
  },
  {
   "type": "fever",
   "lane": 3,
   "startTimeMs": 34285
  },
  {
   "type": "tap",
   "lane": 1,
   "startTimeMs": 34553
  },
  {
   "type": "tap",
   "lane": 0,
   "startTimeMs": 34821
  },
  {
   "type": "hold",
   "lane": 1,
   "startTimeMs": 35357,
   "endTimeMs": 35892
  },
  {
   "type": "tap",
   "lane": 3,
   "startTimeMs": 35892
  },
  {
   "type": "tap",
   "lane": 2,
   "startTimeMs": 36428
  },
  {
   "type": "tap",
   "lane": 3,
   "startTimeMs": 36964
  },
  {
   "type": "hold",
   "lane": 1,
   "startTimeMs": 37500,
   "endTimeMs": 38035
  },
  {
   "type": "tap",
   "lane": 0,
   "startTimeMs": 38035
  },
  {
   "type": "tap",
   "lane": 1,
   "startTimeMs": 47142
  },
  {
   "type": "tap",
   "lane": 2,
   "startTimeMs": 48749
  },
  {
   "type": "tap",
   "lane": 2,
   "startTimeMs": 50892
  },
  {
   "type": "fever",
   "lane": 3,
   "startTimeMs": 51428
  },
  {
   "type": "tap",
   "lane": 2,
   "startTimeMs": 51964
  },
  {
   "type": "tap",
   "lane": 0,
   "startTimeMs": 53035
  },
  {
   "type": "tap",
   "lane": 1,
   "startTimeMs": 54107
  },
  {
   "type": "tap",
   "lane": 0,
   "startTimeMs": 55178
  },
  {
   "type": "golden",
   "lane": 1,
   "startTimeMs": 55714
  },
  {
   "type": "tap",
   "lane": 3,
   "startTimeMs": 55982
  },
  {
   "type": "tap",
   "lane": 2,
   "startTimeMs": 56250
  },
  {
   "type": "hold",
   "lane": 3,
   "startTimeMs": 56785,
   "endTimeMs": 57320
  },
  {
   "type": "tap",
   "lane": 1,
   "startTimeMs": 57321
  },
  {
   "type": "tap",
   "lane": 0,
   "startTimeMs": 57857
  },
  {
   "type": "tap",
   "lane": 1,
   "startTimeMs": 58392
  },
  {
   "type": "hold",
   "lane": 3,
   "startTimeMs": 58928,
   "endTimeMs": 59463
  },
  {
   "type": "tap",
   "lane": 2,
   "startTimeMs": 59464
  },
  {
   "type": "tap",
   "lane": 3,
   "startTimeMs": 60000
  },
  {
   "type": "tap",
   "lane": 1,
   "startTimeMs": 60267
  },
  {
   "type": "tap",
   "lane": 0,
   "startTimeMs": 60535
  },
  {
   "type": "hold",
   "lane": 1,
   "startTimeMs": 61071,
   "endTimeMs": 61606
  },
  {
   "type": "tap",
   "lane": 3,
   "startTimeMs": 61607
  },
  {
   "type": "tap",
   "lane": 2,
   "startTimeMs": 62142
  },
  {
   "type": "tap",
   "lane": 3,
   "startTimeMs": 62678
  },
  {
   "type": "tap",
   "lane": 0,
   "startTimeMs": 63749
  },
  {
   "type": "golden",
   "lane": 1,
   "startTimeMs": 64285
  },
  {
   "type": "tap",
   "lane": 3,
   "startTimeMs": 64553
  },
  {
   "type": "tap",
   "lane": 2,
   "startTimeMs": 64821
  },
  {
   "type": "tap",
   "lane": 1,
   "startTimeMs": 65892
  },
  {
   "type": "tap",
   "lane": 0,
   "startTimeMs": 66428
  },
  {
   "type": "tap",
   "lane": 1,
   "startTimeMs": 66964
  },
  {
   "type": "fever",
   "lane": 3,
   "startTimeMs": 68571
  },
  {
   "type": "tap",
   "lane": 1,
   "startTimeMs": 68839
  },
  {
   "type": "tap",
   "lane": 0,
   "startTimeMs": 69107
  },
  {
   "type": "hold",
   "lane": 1,
   "startTimeMs": 69642,
   "endTimeMs": 70177
  },
  {
   "type": "tap",
   "lane": 3,
   "startTimeMs": 70178
  },
  {
   "type": "tap",
   "lane": 2,
   "startTimeMs": 70714
  },
  {
   "type": "tap",
   "lane": 3,
   "startTimeMs": 71250
  },
  {
   "type": "hold",
   "lane": 1,
   "startTimeMs": 71785,
   "endTimeMs": 72320
  },
  {
   "type": "tap",
   "lane": 0,
   "startTimeMs": 72321
  }
 ]
}