{
 "songId": "rasa_sayange",
 "difficulty": "Normal",
 "bpm": 100,
 "offsetMs": 0,
 "notes": [
  {
   "type": "tap",
   "lane": 1,
   "startTimeMs": 4800
  },
  {
   "type": "tap",
   "lane": 3,
   "startTimeMs": 5100
  },
  {
   "type": "tap",
   "lane": 3,
   "startTimeMs": 5699
  },
  {
   "type": "tap",
   "lane": 0,
   "startTimeMs": 6300
  },
  {
   "type": "tap",
   "lane": 1,
   "startTimeMs": 6600
  },
  {
   "type": "tap",
   "lane": 0,
   "startTimeMs": 7199
  },
  {
   "type": "tap",
   "lane": 1,
   "startTimeMs": 8100
  },
  {
   "type": "tap",
   "lane": 3,
   "startTimeMs": 8399
  },
  {
   "type": "tap",
   "lane": 2,
   "startTimeMs": 8700
  },
  {
   "type": "tap",
   "lane": 1,
   "startTimeMs": 9299
  },
  {
   "type": "tap",
   "lane": 0,
   "startTimeMs": 9900
  },
  {
   "type": "tap",
   "lane": 0,
   "startTimeMs": 10500
  },
  {
   "type": "tap",
   "lane": 1,
   "startTimeMs": 11399
  },
  {
   "type": "tap",
   "lane": 3,
   "startTimeMs": 11700
  },
  {
   "type": "tap",
   "lane": 2,
   "startTimeMs": 12300
  },
  {
   "type": "tap",
   "lane": 1,
   "startTimeMs": 12600
  },
  {
   "type": "tap",
   "lane": 2,
   "startTimeMs": 12900
  },
  {
   "type": "tap",
   "lane": 3,
   "startTimeMs": 13500
  },
  {
   "type": "tap",
   "lane": 1,
   "startTimeMs": 14999
  },
  {
   "type": "tap",
   "lane": 2,
   "startTimeMs": 15299
  },
  {
   "type": "tap",
   "lane": 0,
   "startTimeMs": 15599
  },
  {
   "type": "tap",
   "lane": 0,
   "startTimeMs": 16200
  },
  {
   "type": "tap",
   "lane": 2,
   "startTimeMs": 18300
  },
  {
   "type": "tap",
   "lane": 3,
   "startTimeMs": 18600
  },
  {
   "type": "tap",
   "lane": 1,
   "startTimeMs": 18900
  },
  {
   "type": "tap",
   "lane": 2,
   "startTimeMs": 19200
  },
  {
   "type": "tap",
   "lane": 0,
   "startTimeMs": 19500
  },
  {
   "type": "tap",
   "lane": 3,
   "startTimeMs": 19800
  },
  {
   "type": "tap",
   "lane": 0,
   "startTimeMs": 20099
  },
  {
   "type": "tap",
   "lane": 1,
   "startTimeMs": 20700
  },
  {
   "type": "tap",
   "lane": 2,
   "startTimeMs": 21000
  },
  {
   "type": "tap",
   "lane": 3,
   "startTimeMs": 22200
  },
  {
   "type": "tap",
   "lane": 2,
   "startTimeMs": 22799
  },
  {
   "type": "tap",
   "lane": 1,
   "startTimeMs": 23099
  },
  {
   "type": "tap",
   "lane": 3,
   "startTimeMs": 24300
  },
  {
   "type": "tap",
   "lane": 2,
   "startTimeMs": 24600
  },
  {
   "type": "tap",
   "lane": 3,
   "startTimeMs": 24900
  },
  {
   "type": "tap",
   "lane": 1,
   "startTimeMs": 25200
  },
  {
   "type": "tap",
   "lane": 1,
   "startTimeMs": 25800
  },
  {
   "type": "tap",
   "lane": 0,
   "startTimeMs": 26400
  },
  {
   "type": "tap",
   "lane": 1,
   "startTimeMs": 27299
  },
  {
   "type": "tap",
   "lane": 3,
   "startTimeMs": 27599
  },
  {
   "type": "tap",
   "lane": 2,
   "startTimeMs": 27900
  },
  {
   "type": "tap",
   "lane": 3,
   "startTimeMs": 28200
  },
  {
   "type": "golden",
   "lane": 2,
   "startTimeMs": 28799
  },
  {
   "type": "tap",
   "lane": 0,
   "startTimeMs": 29099
  },
  {
   "type": "tap",
   "lane": 0,
   "startTimeMs": 29699
  },
  {
   "type": "tap",
   "lane": 1,
   "startTimeMs": 30599
  },
  {
   "type": "tap",
   "lane": 3,
   "startTimeMs": 30900
  },
  {
   "type": "tap",
   "lane": 0,
   "startTimeMs": 31200
  },
  {
   "type": "tap",
   "lane": 1,
   "startTimeMs": 31800
  },
  {
   "type": "tap",
   "lane": 2,
   "startTimeMs": 32100
  },
  {
   "type": "tap",
   "lane": 0,
   "startTimeMs": 32400
  },
  {
   "type": "tap",
   "lane": 3,
   "startTimeMs": 32700
  },
  {
   "type": "tap",
   "lane": 2,
   "startTimeMs": 33900
  },
  {
   "type": "tap",
   "lane": 1,
   "startTimeMs": 34200
  },
  {
   "type": "tap",
   "lane": 2,
   "startTimeMs": 34500
  },
  {
   "type": "tap",
   "lane": 0,
   "startTimeMs": 34800
  },
  {
   "type": "tap",
   "lane": 0,
   "startTimeMs": 35400
  },
  {
   "type": "tap",
   "lane": 3,
   "startTimeMs": 36000
  },
  {
   "type": "tap",
   "lane": 2,
   "startTimeMs": 37500
  },
  {
   "type": "tap",
   "lane": 3,
   "startTimeMs": 37800
  },
  {
   "type": "tap",
   "lane": 1,
   "startTimeMs": 38100
  },
  {
   "type": "tap",
   "lane": 0,
   "startTimeMs": 38699
  },
  {
   "type": "tap",
   "lane": 3,
   "startTimeMs": 39000
  },
  {
   "type": "tap",
   "lane": 2,
   "startTimeMs": 39600
  },
  {
   "type": "tap",
   "lane": 3,
   "startTimeMs": 41699
  },
  {
   "type": "tap",
   "lane": 1,
   "startTimeMs": 42599
  },
  {
   "type": "tap",
   "lane": 0,
   "startTimeMs": 43199
  },
  {
   "type": "tap",
   "lane": 1,
   "startTimeMs": 43800
  },
  {
   "type": "tap",
   "lane": 0,
   "startTimeMs": 44699
  },
  {
   "type": "tap",
   "lane": 0,
   "startTimeMs": 45600
  },
  {
   "type": "tap",
   "lane": 2,
   "startTimeMs": 45900
  },
  {
   "type": "tap",
   "lane": 1,
   "startTimeMs": 46200
  },
  {
   "type": "tap",
   "lane": 2,
   "startTimeMs": 46500
  },
  {
   "type": "tap",
   "lane": 0,
   "startTimeMs": 46800
  },
  {
   "type": "tap",
   "lane": 3,
   "startTimeMs": 47100
  },
  {
   "type": "tap",
   "lane": 0,
   "startTimeMs": 47400
  },
  {
   "type": "tap",
   "lane": 3,
   "startTimeMs": 48000
  },
  {
   "type": "tap",
   "lane": 1,
   "startTimeMs": 48300
  },
  {
   "type": "tap",
   "lane": 1,
   "startTimeMs": 48900
  },
  {
   "type": "tap",
   "lane": 2,
   "startTimeMs": 49800
  },
  {
   "type": "tap",
   "lane": 0,
   "startTimeMs": 50100
  },
  {
   "type": "tap",
   "lane": 3,
   "startTimeMs": 50699
  },
  {
   "type": "tap",
   "lane": 3,
   "startTimeMs": 53099
  },
  {
   "type": "tap",
   "lane": 2,
   "startTimeMs": 53400
  },
  {
   "type": "tap",
   "lane": 3,
   "startTimeMs": 53699
  },
  {
   "type": "tap",
   "lane": 1,
   "startTimeMs": 54000
  },
  {
   "type": "tap",
   "lane": 0,
   "startTimeMs": 54300
  },
  {
   "type": "tap",
   "lane": 1,
   "startTimeMs": 54599
  },
  {
   "type": "tap",
   "lane": 3,
   "startTimeMs": 54900
  },
  {
   "type": "tap",
   "lane": 2,
   "startTimeMs": 55499
  },
  {
   "type": "tap",
   "lane": 0,
   "startTimeMs": 56400
  },
  {
   "type": "tap",
   "lane": 0,
   "startTimeMs": 56999
  },
  {
   "type": "tap",
   "lane": 2,
   "startTimeMs": 57300
  },
  {
   "type": "tap",
   "lane": 1,
   "startTimeMs": 57899
  },
  {
   "type": "tap",
   "lane": 1,
   "startTimeMs": 59699
  },
  {
   "type": "tap",
   "lane": 0,
   "startTimeMs": 60300
  },
  {
   "type": "tap",
   "lane": 3,
   "startTimeMs": 60600
  },
  {
   "type": "tap",
   "lane": 0,
   "startTimeMs": 60900
  },
  {
   "type": "tap",
   "lane": 2,
   "startTimeMs": 61200
  },
  {
   "type": "tap",
   "lane": 2,
   "startTimeMs": 61800
  },
  {
   "type": "tap",
   "lane": 0,
   "startTimeMs": 62100
  },
  {
   "type": "tap",
   "lane": 3,
   "startTimeMs": 63000
  },
  {
   "type": "tap",
   "lane": 0,
   "startTimeMs": 63300
  },
  {
   "type": "tap",
   "lane": 2,
   "startTimeMs": 63600
  },
  {
   "type": "tap",
   "lane": 1,
   "startTimeMs": 63900
  },
  {
   "type": "tap",
   "lane": 0,
   "startTimeMs": 64500
  },
  {
   "type": "tap",
   "lane": 2,
   "startTimeMs": 65399
  },
  {
   "type": "tap",
   "lane": 3,
   "startTimeMs": 65700
  },
  {
   "type": "tap",
   "lane": 1,
   "startTimeMs": 66000
  }
 ]
}